cjm_fasthtml_resources/__init__.py
cjm_fasthtml_resources/_modidx.py
cjm_fasthtml_resources/core/__init__.py
cjm_fasthtml_resources/core/management_config.py
cjm_fasthtml_resources/core/manager.py
cjm_fasthtml_resources/core/monitoring_config.py
cjm_fasthtml_resources/core/validation.py
cjm_fasthtml_resources/utils/__init__.py
cjm_fasthtml_resources/utils/plugin_utils.py
cjm_fasthtml_resources-0.0.7.dist-info/licenses/LICENSE
cjm_fasthtml_resources-0.0.7.dist-info/METADATA
cjm_fasthtml_resources-0.0.7.dist-info/WHEEL
cjm_fasthtml_resources-0.0.7.dist-info/entry_points.txt
cjm_fasthtml_resources-0.0.7.dist-info/top_level.txt
cjm_fasthtml_resources-0.0.7.dist-info/RECORD
